saltext/bitwarden/__init__.py
saltext/bitwarden/loader.py
saltext/bitwarden/version.py
saltext/bitwarden/modules/bitwarden_mod.py
saltext/bitwarden/runners/bitwarden_mod.py
saltext/bitwarden/sdb/bitwarden_mod.py
saltext/bitwarden/states/bitwarden_mod.py
saltext/bitwarden/utils/bitwarden_cli.py
saltext/bitwarden/utils/bitwarden_general.py
saltext/bitwarden/utils/bitwarden_vault.py
saltext.bitwarden-0.0.1b15.dist-info/LICENSE
saltext.bitwarden-0.0.1b15.dist-info/METADATA
saltext.bitwarden-0.0.1b15.dist-info/WHEEL
saltext.bitwarden-0.0.1b15.dist-info/entry_points.txt
saltext.bitwarden-0.0.1b15.dist-info/top_level.txt
saltext.bitwarden-0.0.1b15.dist-info/RECORD
